{"cameraMode":{"drawMode":0,"name":"Shaded","section":"Shading Mode"},"sceneLighting":true,"audioPlay":false,"sceneViewState":{"showFog":true,"showMaterialUpdate":false,"showSkybox":true,"showFlares":true,"showImageEffects":true,"showParticleSystems":true},"in2DMode":false,"pivot":{"x":126.53850555419922,"y":6.778895378112793,"z":83.08431243896485},"rotation":{"x":-0.018263250589370729,"y":0.493284672498703,"z":0.010360154323279858,"w":0.8696144819259644},"size":123.34213256835938,"orthographic":false}